bitxchange/__init__.py
bitxchange/__version__.py
bitxchange/api.py
bitxchange/errors.py
bitxchange/lib/__init__.py
bitxchange/lib/shared_utils.py
bitxchange/spot/__init__.py
bitxchange/spot/account.py
bitxchange/spot/market.py
bitxchange_py_api-0.0.2.dist-info/LICENSE
bitxchange_py_api-0.0.2.dist-info/METADATA
bitxchange_py_api-0.0.2.dist-info/WHEEL
bitxchange_py_api-0.0.2.dist-info/top_level.txt
bitxchange_py_api-0.0.2.dist-info/RECORD
