Metadata-Version: 2.1
Name: bitxchange-py-api
Version: 0.0.2
Summary: Offical Bitxchange python API library
Home-page: https://github.com/Wozinga/bitxchange_python_api
License: MIT
Keywords: Bitxchange,Public API
Platform: UNKNOWN
Classifier: Intended Audience :: Developers
Classifier: Intended Audience :: Financial and Insurance Industry
Classifier: License :: OSI Approved :: MIT License
Classifier: Programming Language :: Python :: 3.6
Classifier: Programming Language :: Python :: 3.7
Classifier: Programming Language :: Python :: 3.8
Classifier: Programming Language :: Python :: 3.9
Requires-Python: >=3.6
Requires-Dist: requests
